yiddish/__init__.py
yiddish/yiddish.py
yiddish/submodules/hasidify_lexicon/anywhere_variants.csv
yiddish/submodules/hasidify_lexicon/ik_exceptions.csv
yiddish/submodules/hasidify_lexicon/last_minute_fixes.csv
yiddish/submodules/hasidify_lexicon/lekh_exceptions.csv
yiddish/submodules/hasidify_lexicon/lkizmen.csv
yiddish/submodules/hasidify_lexicon/prefix_variants.csv
yiddish/submodules/hasidify_lexicon/suffix_variants.csv
yiddish/submodules/hasidify_lexicon/whole_word_variants.csv
yiddish/submodules/hasidify_lexicon/word_group_variants.csv
yiddish/submodules/loshn-koydesh-pronunciation/orthographic-to-phonetic.txt
yiddish/submodules/loshn-koydesh-pronunciation/phonetic-to-orthographic.txt
yiddish-0.0.23.dist-info/LICENSE.md
yiddish-0.0.23.dist-info/METADATA
yiddish-0.0.23.dist-info/WHEEL
yiddish-0.0.23.dist-info/top_level.txt
yiddish-0.0.23.dist-info/RECORD
