Metadata-Version: 2.1
Name: yiddish
Version: 0.0.23
Summary: A Python library for processing Yiddish text
Home-page: https://github.com/ibleaman/yiddish
Author: Isaac L. Bleaman
Author-email: bleaman@berkeley.edu
License: MIT
License-File: LICENSE.md
